pegasus/Pegasus.py
pegasus/__init__.py
pegasus/cli.py
pegasus_surf-0.2.4.dist-info/METADATA
pegasus_surf-0.2.4.dist-info/WHEEL
pegasus_surf-0.2.4.dist-info/entry_points.txt
pegasus_surf-0.2.4.dist-info/top_level.txt
pegasus_surf-0.2.4.dist-info/RECORD
