Metadata-Version: 2.1
Name: pegasus-surf
Version: 0.2.4
Summary: A package for scraping websites and converting them to Markdown
Home-page: https://github.com/Sunwood-ai-labs/PEGASUS
Author: Maki
Author-email: sunwood.ai.labs@gmail.com
Classifier: Development Status :: 3 - Alpha
Classifier: Intended Audience :: Developers
Classifier: License :: OSI Approved :: MIT License
Classifier: Programming Language :: Python :: 3
Classifier: Programming Language :: Python :: 3.6
Classifier: Programming Language :: Python :: 3.7
Classifier: Programming Language :: Python :: 3.8
Classifier: Programming Language :: Python :: 3.9
Requires-Dist: requests
Requires-Dist: markdownify
Requires-Dist: beautifulsoup4
Requires-Dist: loguru
Requires-Dist: art
Requires-Dist: litellm
Requires-Dist: python-dotenv
Requires-Dist: google-generativeai
